MANIFEST.in
README.rst
elfinder.py
requirements.txt
setup.py
elfinder.egg-info/PKG-INFO
elfinder.egg-info/SOURCES.txt
elfinder.egg-info/dependency_links.txt
elfinder.egg-info/pbr.json
elfinder.egg-info/requires.txt
elfinder.egg-info/top_level.txt